deapp/__init__.py
deapp/ci1.py
deapp/ci2.py
deapp/ci3.py
deapp/ci4.py
deapp/ci5.py
deapp/dc1.py
deapp/dc2.py
deapp/dc3.py
deapp/dc4.py
deapp/dc5.py
deappp-0.1.dist-info/METADATA
deappp-0.1.dist-info/WHEEL
deappp-0.1.dist-info/top_level.txt
deappp-0.1.dist-info/RECORD
