Metadata-Version: 2.1
Name: deappp
Version: 0.1
Summary: Educational package for simple BI code examples.
Home-page: https://github.com/yourusername/your_package_name
Author: Aniket Chavan
Author-email: caniket975@gmail.com
Classifier: Programming Language :: Python :: 3
Classifier: License :: OSI Approved :: MIT License
Classifier: Operating System :: OS Independent
Requires-Python: >=3.7
Requires-Dist: numpy
Requires-Dist: pandas
